because/__init__.py
because/templib_cli.py
because-1.0.0.dist-info/LICENSE
because-1.0.0.dist-info/METADATA
because-1.0.0.dist-info/WHEEL
because-1.0.0.dist-info/RECORD
